<?xml version="1.0" encoding="UTF-8"?><record_update>
    <sys_ui_section action="DELETE" caption="New Section" section_id="e3b4aaec1bb01010c8beed3abc4bcbe4" sys_domain="global" table="x_58872_needit_needit" version="3" view="User">
        <sys_ui_element action="INSERT_OR_UPDATE">
            <element>short_description</element>
            <position>0</position>
            <sys_created_by>admin</sys_created_by>
            <sys_created_on>2020-05-12 15:13:27</sys_created_on>
            <sys_id>6fb4eaec1bb01010c8beed3abc4bcb0b</sys_id>
            <sys_mod_count>0</sys_mod_count>
            <sys_ui_formatter/>
            <sys_ui_section caption="New Section" display_value="New Section" name="x_58872_needit_needit" sys_domain="global" view="5bd975bd0fa03200cd674f8ce1050e7f">e3b4aaec1bb01010c8beed3abc4bcbe4</sys_ui_section>
            <sys_updated_by>admin</sys_updated_by>
            <sys_updated_on>2020-05-12 15:13:27</sys_updated_on>
            <sys_user/>
            <type/>
        </sys_ui_element>
        <sys_ui_element action="INSERT_OR_UPDATE">
            <element>description</element>
            <position>1</position>
            <sys_created_by>admin</sys_created_by>
            <sys_created_on>2020-05-12 15:13:27</sys_created_on>
            <sys_id>efb4eaec1bb01010c8beed3abc4bcb0b</sys_id>
            <sys_mod_count>0</sys_mod_count>
            <sys_ui_formatter/>
            <sys_ui_section caption="New Section" display_value="New Section" name="x_58872_needit_needit" sys_domain="global" view="5bd975bd0fa03200cd674f8ce1050e7f">e3b4aaec1bb01010c8beed3abc4bcbe4</sys_ui_section>
            <sys_updated_by>admin</sys_updated_by>
            <sys_updated_on>2020-05-12 15:13:27</sys_updated_on>
            <sys_user/>
            <type/>
        </sys_ui_element>
        <sys_ui_section action="DELETE">
            <caption>New Section</caption>
            <header>false</header>
            <name>x_58872_needit_needit</name>
            <roles/>
            <sys_class_name>sys_ui_section</sys_class_name>
            <sys_created_by>admin</sys_created_by>
            <sys_created_on>2020-05-12 15:13:26</sys_created_on>
            <sys_domain>global</sys_domain>
            <sys_domain_path>/</sys_domain_path>
            <sys_id>e3b4aaec1bb01010c8beed3abc4bcbe4</sys_id>
            <sys_mod_count>0</sys_mod_count>
            <sys_name>New Section</sys_name>
            <sys_overrides/>
            <sys_package display_value="NeedIt" source="x_58872_needit">6ead8e780f603200cd674f8ce1050ed1</sys_package>
            <sys_policy/>
            <sys_scope display_value="NeedIt">6ead8e780f603200cd674f8ce1050ed1</sys_scope>
            <sys_update_name>sys_ui_section_e3b4aaec1bb01010c8beed3abc4bcbe4</sys_update_name>
            <sys_updated_by>admin</sys_updated_by>
            <sys_updated_on>2020-05-12 15:13:26</sys_updated_on>
            <sys_user/>
            <title>false</title>
            <view display_value="User" name="User">5bd975bd0fa03200cd674f8ce1050e7f</view>
            <view_name/>
        </sys_ui_section>
    </sys_ui_section>
    <sys_update_version action="INSERT_OR_UPDATE">
        <action>DELETE</action>
        <application display_value="NeedIt">6ead8e780f603200cd674f8ce1050ed1</application>
        <file_path/>
        <instance_id>9a055ceddb12f7409df22f17d496199e</instance_id>
        <instance_name>dev88756</instance_name>
        <name>sys_ui_section_e3b4aaec1bb01010c8beed3abc4bcbe4</name>
        <payload><![CDATA[<?xml version="1.0" encoding="UTF-8"?><record_update><sys_ui_section caption="New Section" section_id="e3b4aaec1bb01010c8beed3abc4bcbe4" sys_domain="global" table="x_58872_needit_needit" version="3" view="User"><sys_ui_element action="INSERT_OR_UPDATE"><element>short_description</element><position>0</position><sys_created_by>admin</sys_created_by><sys_created_on>2020-05-12 15:13:27</sys_created_on><sys_id>6fb4eaec1bb01010c8beed3abc4bcb0b</sys_id><sys_mod_count>0</sys_mod_count><sys_ui_formatter/><sys_ui_section caption="New Section" display_value="New Section" name="x_58872_needit_needit" sys_domain="global" view="5bd975bd0fa03200cd674f8ce1050e7f">e3b4aaec1bb01010c8beed3abc4bcbe4</sys_ui_section><sys_updated_by>admin</sys_updated_by><sys_updated_on>2020-05-12 15:13:27</sys_updated_on><sys_user/><type/></sys_ui_element><sys_ui_element action="INSERT_OR_UPDATE"><element>description</element><position>1</position><sys_created_by>admin</sys_created_by><sys_created_on>2020-05-12 15:13:27</sys_created_on><sys_id>efb4eaec1bb01010c8beed3abc4bcb0b</sys_id><sys_mod_count>0</sys_mod_count><sys_ui_formatter/><sys_ui_section caption="New Section" display_value="New Section" name="x_58872_needit_needit" sys_domain="global" view="5bd975bd0fa03200cd674f8ce1050e7f">e3b4aaec1bb01010c8beed3abc4bcbe4</sys_ui_section><sys_updated_by>admin</sys_updated_by><sys_updated_on>2020-05-12 15:13:27</sys_updated_on><sys_user/><type/></sys_ui_element><sys_ui_section action="INSERT_OR_UPDATE"><caption>New Section</caption><header>false</header><name>x_58872_needit_needit</name><roles/><sys_class_name>sys_ui_section</sys_class_name><sys_created_by>admin</sys_created_by><sys_created_on>2020-05-12 15:13:26</sys_created_on><sys_domain>global</sys_domain><sys_domain_path>/</sys_domain_path><sys_id>e3b4aaec1bb01010c8beed3abc4bcbe4</sys_id><sys_mod_count>0</sys_mod_count><sys_name>New Section</sys_name><sys_overrides/><sys_package display_value="NeedIt" source="x_58872_needit">6ead8e780f603200cd674f8ce1050ed1</sys_package><sys_policy/><sys_scope display_value="NeedIt">6ead8e780f603200cd674f8ce1050ed1</sys_scope><sys_update_name>sys_ui_section_e3b4aaec1bb01010c8beed3abc4bcbe4</sys_update_name><sys_updated_by>admin</sys_updated_by><sys_updated_on>2020-05-12 15:13:26</sys_updated_on><sys_user/><title>false</title><view display_value="User" name="User">5bd975bd0fa03200cd674f8ce1050e7f</view><view_name/></sys_ui_section></sys_ui_section></record_update>]]></payload>
        <payload_hash>278951088</payload_hash>
        <record_name>NeedIt</record_name>
        <reverted_from/>
        <source>a4cdc6ac1b701010c8beed3abc4bcb19</source>
        <source_table>sys_update_set</source_table>
        <state>previous</state>
        <sys_created_by>admin</sys_created_by>
        <sys_created_on>2020-05-12 15:13:27</sys_created_on>
        <sys_id>67b4eaec1bb01010c8beed3abc4bcb0d</sys_id>
        <sys_mod_count>0</sys_mod_count>
        <sys_recorded_at>1720972a31c0000001</sys_recorded_at>
        <sys_updated_by>admin</sys_updated_by>
        <sys_updated_on>2020-05-12 15:13:27</sys_updated_on>
        <type>Form Layout</type>
        <update_guid>efb4eaec39b0101068f94ea397dce40c</update_guid>
        <update_guid_history>efb4eaec39b0101068f94ea397dce40c:278951088</update_guid_history>
    </sys_update_version>
    <sys_metadata_delete action="INSERT_OR_UPDATE">
        <sys_audit_delete/>
        <sys_class_name>sys_metadata_delete</sys_class_name>
        <sys_created_by>admin</sys_created_by>
        <sys_created_on>2020-05-12 15:14:19</sys_created_on>
        <sys_db_object display_value="" name="sys_ui_section">sys_ui_section</sys_db_object>
        <sys_id>672e828cd3864bd0b629757c4f3a2910</sys_id>
        <sys_metadata>e3b4aaec1bb01010c8beed3abc4bcbe4</sys_metadata>
        <sys_mod_count>0</sys_mod_count>
        <sys_name>New Section</sys_name>
        <sys_package display_value="NeedIt" source="x_58872_needit">6ead8e780f603200cd674f8ce1050ed1</sys_package>
        <sys_parent display_value="NeedIt">2a341ea01bb01010c8beed3abc4bcba6</sys_parent>
        <sys_policy/>
        <sys_scope display_value="NeedIt">6ead8e780f603200cd674f8ce1050ed1</sys_scope>
        <sys_scope_delete display_value="">94872a8897db403e8ee69a431de2fca4</sys_scope_delete>
        <sys_update_name>sys_ui_section_e3b4aaec1bb01010c8beed3abc4bcbe4</sys_update_name>
        <sys_update_version display_value="sys_ui_section_e3b4aaec1bb01010c8beed3abc4bcbe4">67b4eaec1bb01010c8beed3abc4bcb0d</sys_update_version>
        <sys_updated_by>admin</sys_updated_by>
        <sys_updated_on>2020-05-12 15:14:19</sys_updated_on>
    </sys_metadata_delete>
</record_update>
